Metadata-Version: 1.0
Name: python-sox
Version: 0.2.1
Summary: Sensor Over XMPP library for python
Home-page: UNKNOWN
Author: Hide. Tokuda Laboratory
Author-email: ht@ht.sfc.keio.ac.jp
License: The MIT License (MIT)
